{"items": [
    {"id":42553,"enchant":3820,"gems":[41285,40049]},
    {"id":39472},
    {"id":37673,"enchant":3810,"gems":[39998]},
    {"id":41610,"enchant":3722},
    {"id":39492,"enchant":3832,"gems":[39998,40049]},
    {"id":37361,"enchant":2332,"gems":[0]},
    {"id":39495,"enchant":3604,"gems":[39998,0]},
    {"id":40696,"gems":[40049,40026]},
    {"id":37854,"enchant":3719},
    {"id":44202,"enchant":3606,"gems":[40026]},
    {"id":40585},
    {"id":37694},
    {"id":37873},
    {"id":40682},
    {"id":37360,"enchant":3854},
    {},
    {"id":37238}
]}