{"items": [
    {"id":42553,"enchant":3819,"gems":[41401,42148]},
    {"id":40681},
    {"id":37655,"enchant":3809},
    {"id":37291,"enchant":3831},
    {"id":39515,"enchant":3832,"gems":[40012,40012]},
    {"id":37361,"enchant":1119,"gems":[0]},
    {"id":39519,"enchant":3604,"gems":[40012,0]},
    {"id":40697,"enchant":3601,"gems":[42148,42148]},
    {"id":37189,"enchant":3719,"gems":[40047,49110]},
    {"id":44202,"enchant":3606,"gems":[40092]},
    {"id":44283},
    {"id":37694},
    {"id":37111},
    {"id":42413,"gems":[40012,40012]},
    {"id":37360,"enchant":3854},
    {},
    {"id":37619}
]}