{"items": [
    {"id":48398,"enchant":3817,"gems":[41398,40117]},
    {"id":47988,"gems":[40117]},
    {"id":48400,"enchant":3808,"gems":[42153]},
    {"id":47546,"enchant":3605,"gems":[40117]},
    {"id":48396,"enchant":3832,"gems":[42153,42153]},
    {"id":47442,"enchant":3845,"gems":[40117,0]},
    {"id":47492,"enchant":3604,"gems":[49110,40117,0]},
    {"id":47472,"gems":[40117,40117,40117]},
    {"id":48399,"enchant":3823,"gems":[40142,40117]},
    {"id":47445,"enchant":3606,"gems":[40117,40117]},
    {"id":48007,"gems":[40117]},
    {"id":45608,"gems":[40117]},
    {"id":46038},
    {"id":47464},
    {"id":47446,"enchant":3789,"gems":[40117,40117]},
    {},
    {"id":47428,"gems":[40117]}
]}